fst_python_bindings-0.2.0.dist-info/METADATA
fst_python_bindings-0.2.0.dist-info/WHEEL
fst_python_bindings-0.2.0.dist-info/license_files/LICENSE.md
fst_python_bindings/__init__.py
fst_python_bindings/fst_python_bindings.cpython-310-x86_64-linux-gnu.so
fst_python_bindings-0.2.0.dist-info/RECORD
