Metadata-Version: 2.1
Name: fst_python_bindings
Version: 0.2.0
License-File: LICENSE.md
Summary: Search over large sets of strings
Keywords: fst,levenstein,fsm,search
Author: Hukumka <hukumka212@gmail.com>
Author-email: hukumka212@gmail.com
Maintainer-email: hukumka <hukumka212@gmail.com>
Requires-Python: >=3.8
Project-URL: repository, https://github.com/hukumka/fst_python_bindings/github.com
